networkzero/config.py
networkzero/core.py
networkzero/discovery.py
networkzero/messenger.py
networkzero/sockets.py
networkzero/__init__.py
networkzero-1.0b1.dist-info/DESCRIPTION.rst
networkzero-1.0b1.dist-info/METADATA
networkzero-1.0b1.dist-info/metadata.json
networkzero-1.0b1.dist-info/RECORD
networkzero-1.0b1.dist-info/top_level.txt
networkzero-1.0b1.dist-info/WHEEL
