Metadata-Version: 1.1
Name: networkzero
Version: 1.0b1
Summary: Making networking simple for teachers
Home-page: https://github.com/tjguk/networkzero
Author: Tim Golden
Author-email: mail@timgolden.me.uk
License: MIT
Keywords: networking education
Platform: UNKNOWN
Classifier: Development Status :: 4 - Beta
Classifier: Intended Audience :: Developers
Classifier: Topic :: Software Development :: Build Tools
Classifier: License :: OSI Approved :: MIT License
Classifier: Programming Language :: Python :: 2
Classifier: Programming Language :: Python :: 2.7
Classifier: Programming Language :: Python :: 3
Classifier: Programming Language :: Python :: 3.3
Classifier: Programming Language :: Python :: 3.4
Classifier: Programming Language :: Python :: 3.5
